<?xml version="1.0" encoding="utf-8"?>
<!--Generated by i-Deate.-->
<!-- Created by IRIS Business Services Limited -->
<link:linkbase xmlns:link="http://www.xbrl.org/2003/linkbase" xmlns:xsi="http://www.w3.org/2001/XMLSchema-instance" xmlns:xlink="http://www.w3.org/1999/xlink" xmlns:xbrli="http://www.xbrl.org/2003/instance" xmlns:in-rbi-rep-par="http://www.rbi.org/in-rbi-rep-par" xsi:schemaLocation="http://www.xbrl.org/2006/ref http://www.xbrl.org/2006/ref-2006-02-27.xsd http://www.xbrl.org/2003/linkbase http://www.xbrl.org/2003/xbrl-linkbase-2003-12-31.xsd http://www.rbi.org/in-rbi-rep-par ../core/in-rbi-rep-par.xsd">
  <link:referenceLink xlink:type="extended" xlink:role="http://www.xbrl.org/2003/role/link">
    <link:loc xlink:type="locator" xlink:href="../core/in-rbi-rep.xsd#in-rbi-rep_SoverignCharacter" xlink:label="in-rbi-rep_SoverignCharacter" />
    <link:reference xlink:type="resource" xlink:label="res_1" xlink:role="http://www.xbrl.org/2003/role/disclosureRef" id="res_1">
      <in-rbi-rep-par:Circular>DBS.No.FBC.BC.3413.12.00199-2000  April 6, 2000</in-rbi-rep-par:Circular>
    </link:reference>
    <link:referenceArc xlink:type="arc" xlink:arcrole="http://www.xbrl.org/2003/arcrole/concept-reference" xlink:from="in-rbi-rep_SoverignCharacter" xlink:to="res_1" />
    <link:loc xlink:type="locator" xlink:href="../core/in-rbi-rep.xsd#in-rbi-rep_CategoryOfBorrower" xlink:label="in-rbi-rep_CategoryOfBorrower" />
    <link:reference xlink:type="resource" xlink:label="res_2" xlink:role="http://www.xbrl.org/2003/role/disclosureRef" id="res_2">
      <in-rbi-rep-par:Circular>DBS.No.FBC.BC.3413.12.00199-2000  April 6, 2000</in-rbi-rep-par:Circular>
    </link:reference>
    <link:referenceArc xlink:type="arc" xlink:arcrole="http://www.xbrl.org/2003/arcrole/concept-reference" xlink:from="in-rbi-rep_CategoryOfBorrower" xlink:to="res_2" />
    <link:loc xlink:type="locator" xlink:href="../core/in-rbi-rep.xsd#in-rbi-rep_AggregateAmountOfLimitsSanctioned" xlink:label="in-rbi-rep_AggregateAmountOfLimitsSanctioned" />
    <link:reference xlink:type="resource" xlink:label="res_3" xlink:role="http://www.xbrl.org/2003/role/disclosureRef" id="res_3">
      <in-rbi-rep-par:Circular>DBS.No.FBC.BC.3413.12.00199-2000  April 6, 2000</in-rbi-rep-par:Circular>
    </link:reference>
    <link:referenceArc xlink:type="arc" xlink:arcrole="http://www.xbrl.org/2003/arcrole/concept-reference" xlink:from="in-rbi-rep_AggregateAmountOfLimitsSanctioned" xlink:to="res_3" />
    <link:loc xlink:type="locator" xlink:href="../core/in-rbi-rep.xsd#in-rbi-rep_AmountOfFundedLimitsSanctioned" xlink:label="in-rbi-rep_AmountOfFundedLimitsSanctioned" />
    <link:reference xlink:type="resource" xlink:label="res_4" xlink:role="http://www.xbrl.org/2003/role/disclosureRef" id="res_4">
      <in-rbi-rep-par:Circular>DBS.No.FBC.BC.3413.12.00199-2000  April 6, 2000</in-rbi-rep-par:Circular>
    </link:reference>
    <link:referenceArc xlink:type="arc" xlink:arcrole="http://www.xbrl.org/2003/arcrole/concept-reference" xlink:from="in-rbi-rep_AmountOfFundedLimitsSanctioned" xlink:to="res_4" />
    <link:loc xlink:type="locator" xlink:href="../core/in-rbi-rep.xsd#in-rbi-rep_AmountOfNonFundedLimitsSanctioned" xlink:label="in-rbi-rep_AmountOfNonFundedLimitsSanctioned" />
    <link:reference xlink:type="resource" xlink:label="res_5" xlink:role="http://www.xbrl.org/2003/role/disclosureRef" id="res_5">
      <in-rbi-rep-par:Circular>DBS.No.FBC.BC.3413.12.00199-2000  April 6, 2000</in-rbi-rep-par:Circular>
    </link:reference>
    <link:referenceArc xlink:type="arc" xlink:arcrole="http://www.xbrl.org/2003/arcrole/concept-reference" xlink:from="in-rbi-rep_AmountOfNonFundedLimitsSanctioned" xlink:to="res_5" />
    <link:loc xlink:type="locator" xlink:href="../core/in-rbi-rep.xsd#in-rbi-rep_AmountOutstandingOfCustomerCreditLimitSenctioned" xlink:label="in-rbi-rep_AmountOutstandingOfCustomerCreditLimitSenctioned" />
    <link:reference xlink:type="resource" xlink:label="res_6" xlink:role="http://www.xbrl.org/2003/role/disclosureRef" id="res_6">
      <in-rbi-rep-par:Circular>DBS.No.FBC.BC.3413.12.00199-2000  April 6, 2000</in-rbi-rep-par:Circular>
    </link:reference>
    <link:referenceArc xlink:type="arc" xlink:arcrole="http://www.xbrl.org/2003/arcrole/concept-reference" xlink:from="in-rbi-rep_AmountOutstandingOfCustomerCreditLimitSenctioned" xlink:to="res_6" />
    <link:loc xlink:type="locator" xlink:href="../core/in-rbi-rep.xsd#in-rbi-rep_SecurityValue" xlink:label="in-rbi-rep_SecurityValue" />
    <link:reference xlink:type="resource" xlink:label="res_7" xlink:role="http://www.xbrl.org/2003/role/disclosureRef" id="res_7">
      <in-rbi-rep-par:Circular>DBS.No.FBC.BC.3413.12.00199-2000  April 6, 2000</in-rbi-rep-par:Circular>
    </link:reference>
    <link:referenceArc xlink:type="arc" xlink:arcrole="http://www.xbrl.org/2003/arcrole/concept-reference" xlink:from="in-rbi-rep_SecurityValue" xlink:to="res_7" />
    <link:loc xlink:type="locator" xlink:href="../core/in-rbi-rep.xsd#in-rbi-rep_AssetsClassification" xlink:label="in-rbi-rep_AssetsClassification" />
    <link:reference xlink:type="resource" xlink:label="res_8" xlink:role="http://www.xbrl.org/2003/role/disclosureRef" id="res_8">
      <in-rbi-rep-par:Circular>DBS.No.FBC.BC.3413.12.00199-2000  April 6, 2000</in-rbi-rep-par:Circular>
    </link:reference>
    <link:referenceArc xlink:type="arc" xlink:arcrole="http://www.xbrl.org/2003/arcrole/concept-reference" xlink:from="in-rbi-rep_AssetsClassification" xlink:to="res_8" />
    <link:loc xlink:type="locator" xlink:href="../core/in-rbi-rep.xsd#in-rbi-rep_AmountOfProvisionsHeldAtBranch" xlink:label="in-rbi-rep_AmountOfProvisionsHeldAtBranch" />
    <link:reference xlink:type="resource" xlink:label="res_9" xlink:role="http://www.xbrl.org/2003/role/disclosureRef" id="res_9">
      <in-rbi-rep-par:Circular>DBS.No.FBC.BC.3413.12.00199-2000  April 6, 2000</in-rbi-rep-par:Circular>
    </link:reference>
    <link:referenceArc xlink:type="arc" xlink:arcrole="http://www.xbrl.org/2003/arcrole/concept-reference" xlink:from="in-rbi-rep_AmountOfProvisionsHeldAtBranch" xlink:to="res_9" />
    <link:loc xlink:type="locator" xlink:href="../core/in-rbi-rep.xsd#in-rbi-rep_AmountOfProvisionsHeldAtHeadOffice" xlink:label="in-rbi-rep_AmountOfProvisionsHeldAtHeadOffice" />
    <link:reference xlink:type="resource" xlink:label="res_10" xlink:role="http://www.xbrl.org/2003/role/disclosureRef" id="res_10">
      <in-rbi-rep-par:Circular>DBS.No.FBC.BC.3413.12.00199-2000  April 6, 2000</in-rbi-rep-par:Circular>
    </link:reference>
    <link:referenceArc xlink:type="arc" xlink:arcrole="http://www.xbrl.org/2003/arcrole/concept-reference" xlink:from="in-rbi-rep_AmountOfProvisionsHeldAtHeadOffice" xlink:to="res_10" />
    <link:loc xlink:type="locator" xlink:href="../core/in-rbi-rep.xsd#in-rbi-rep_AmountOfInterestSuspense" xlink:label="in-rbi-rep_AmountOfInterestSuspense" />
    <link:reference xlink:type="resource" xlink:label="res_11" xlink:role="http://www.xbrl.org/2003/role/disclosureRef" id="res_11">
      <in-rbi-rep-par:Circular>DBS.No.FBC.BC.3413.12.00199-2000  April 6, 2000</in-rbi-rep-par:Circular>
    </link:reference>
    <link:referenceArc xlink:type="arc" xlink:arcrole="http://www.xbrl.org/2003/arcrole/concept-reference" xlink:from="in-rbi-rep_AmountOfInterestSuspense" xlink:to="res_11" />
    <link:loc xlink:type="locator" xlink:href="../core/in-rbi-rep.xsd#in-rbi-rep_AggregateAmountOfProvisionAndInterestSuspense" xlink:label="in-rbi-rep_AggregateAmountOfProvisionAndInterestSuspense" />
    <link:reference xlink:type="resource" xlink:label="res_12" xlink:role="http://www.xbrl.org/2003/role/disclosureRef" id="res_12">
      <in-rbi-rep-par:Circular>DBS.No.FBC.BC.3413.12.00199-2000  April 6, 2000</in-rbi-rep-par:Circular>
    </link:reference>
    <link:referenceArc xlink:type="arc" xlink:arcrole="http://www.xbrl.org/2003/arcrole/concept-reference" xlink:from="in-rbi-rep_AggregateAmountOfProvisionAndInterestSuspense" xlink:to="res_12" />
    <link:loc xlink:type="locator" xlink:href="../core/in-rbi-rep.xsd#in-rbi-rep_AmountOfProvisionRequiredToBeHeldByRegulatoryAuthorities" xlink:label="in-rbi-rep_AmountOfProvisionRequiredToBeHeldByRegulatoryAuthorities" />
    <link:reference xlink:type="resource" xlink:label="res_13" xlink:role="http://www.xbrl.org/2003/role/disclosureRef" id="res_13">
      <in-rbi-rep-par:Circular>DBS.No.FBC.BC.3413.12.00199-2000  April 6, 2000</in-rbi-rep-par:Circular>
    </link:reference>
    <link:referenceArc xlink:type="arc" xlink:arcrole="http://www.xbrl.org/2003/arcrole/concept-reference" xlink:from="in-rbi-rep_AmountOfProvisionRequiredToBeHeldByRegulatoryAuthorities" xlink:to="res_13" />
    <link:loc xlink:type="locator" xlink:href="../core/in-rbi-rep.xsd#in-rbi-rep_AmountOfShortFall" xlink:label="in-rbi-rep_AmountOfShortFall" />
    <link:reference xlink:type="resource" xlink:label="res_14" xlink:role="http://www.xbrl.org/2003/role/disclosureRef" id="res_14">
      <in-rbi-rep-par:Circular>DBS.No.FBC.BC.3413.12.00199-2000  April 6, 2000</in-rbi-rep-par:Circular>
    </link:reference>
    <link:referenceArc xlink:type="arc" xlink:arcrole="http://www.xbrl.org/2003/arcrole/concept-reference" xlink:from="in-rbi-rep_AmountOfShortFall" xlink:to="res_14" />
    <link:loc xlink:type="locator" xlink:href="../core/in-rbi-rep.xsd#in-rbi-rep_AmountOfHeadOfficeSupportFund" xlink:label="in-rbi-rep_AmountOfHeadOfficeSupportFund" />
    <link:reference xlink:type="resource" xlink:label="res_15" xlink:role="http://www.xbrl.org/2003/role/disclosureRef" id="res_15">
      <in-rbi-rep-par:Circular>DBS.No.FBC.BC.3413.12.00199-2000  April 6, 2000</in-rbi-rep-par:Circular>
    </link:reference>
    <link:referenceArc xlink:type="arc" xlink:arcrole="http://www.xbrl.org/2003/arcrole/concept-reference" xlink:from="in-rbi-rep_AmountOfHeadOfficeSupportFund" xlink:to="res_15" />
    <link:loc xlink:type="locator" xlink:href="../core/in-rbi-rep.xsd#in-rbi-rep_DevelopmentsDuringQuarter" xlink:label="in-rbi-rep_DevelopmentsDuringQuarter" />
    <link:reference xlink:type="resource" xlink:label="res_16" xlink:role="http://www.xbrl.org/2003/role/disclosureRef" id="res_16">
      <in-rbi-rep-par:Circular>DBS.No.FBC.BC.3413.12.00199-2000  April 6, 2000</in-rbi-rep-par:Circular>
    </link:reference>
    <link:referenceArc xlink:type="arc" xlink:arcrole="http://www.xbrl.org/2003/arcrole/concept-reference" xlink:from="in-rbi-rep_DevelopmentsDuringQuarter" xlink:to="res_16" />
    <link:loc xlink:type="locator" xlink:href="../core/in-rbi-rep.xsd#in-rbi-rep_AggregateAmountOfProvision" xlink:label="in-rbi-rep_AggregateAmountOfProvision" />
    <link:reference xlink:type="resource" xlink:label="res_17" xlink:role="http://www.xbrl.org/2003/role/disclosureRef" id="res_17">
      <in-rbi-rep-par:Circular>DBS.No.FBC.BC.3413.12.00199-2000  April 6, 2000</in-rbi-rep-par:Circular>
    </link:reference>
    <link:referenceArc xlink:type="arc" xlink:arcrole="http://www.xbrl.org/2003/arcrole/concept-reference" xlink:from="in-rbi-rep_AggregateAmountOfProvision" xlink:to="res_17" />
    <link:loc xlink:type="locator" xlink:href="../core/in-rbi-rep.xsd#in-rbi-rep_AmountOfBookValueOfCreditSanctioned" xlink:label="in-rbi-rep_AmountOfBookValueOfCreditSanctioned" />
    <link:reference xlink:type="resource" xlink:label="res_18" xlink:role="http://www.xbrl.org/2003/role/disclosureRef" id="res_18">
      <in-rbi-rep-par:Circular>DBS.No.FBC.BC.3413.12.00199-2000  April 6, 2000</in-rbi-rep-par:Circular>
    </link:reference>
    <link:referenceArc xlink:type="arc" xlink:arcrole="http://www.xbrl.org/2003/arcrole/concept-reference" xlink:from="in-rbi-rep_AmountOfBookValueOfCreditSanctioned" xlink:to="res_18" />
    <link:loc xlink:type="locator" xlink:href="../core/in-rbi-rep.xsd#in-rbi-rep_AmountOfMarketValueOfCreditSanctioned" xlink:label="in-rbi-rep_AmountOfMarketValueOfCreditSanctioned" />
    <link:reference xlink:type="resource" xlink:label="res_19" xlink:role="http://www.xbrl.org/2003/role/disclosureRef" id="res_19">
      <in-rbi-rep-par:Circular>DBS.No.FBC.BC.3413.12.00199-2000  April 6, 2000</in-rbi-rep-par:Circular>
    </link:reference>
    <link:referenceArc xlink:type="arc" xlink:arcrole="http://www.xbrl.org/2003/arcrole/concept-reference" xlink:from="in-rbi-rep_AmountOfMarketValueOfCreditSanctioned" xlink:to="res_19" />
    <link:loc xlink:type="locator" xlink:href="../core/in-rbi-rep.xsd#in-rbi-rep_MoreThanUSD1MiliionMember" xlink:label="in-rbi-rep_MoreThanUSD1MiliionMember" />
    <link:reference xlink:type="resource" xlink:label="res_20" xlink:role="http://www.xbrl.org/2003/role/disclosureRef" id="res_20">
      <in-rbi-rep-par:Circular>DBS.No.FBC.BC.3413.12.00199-2000  April 6, 2000</in-rbi-rep-par:Circular>
    </link:reference>
    <link:referenceArc xlink:type="arc" xlink:arcrole="http://www.xbrl.org/2003/arcrole/concept-reference" xlink:from="in-rbi-rep_MoreThanUSD1MiliionMember" xlink:to="res_20" />
    <link:loc xlink:type="locator" xlink:href="../core/in-rbi-rep.xsd#in-rbi-rep_LessThanUSD1MiliionMember" xlink:label="in-rbi-rep_LessThanUSD1MiliionMember" />
    <link:reference xlink:type="resource" xlink:label="res_21" xlink:role="http://www.xbrl.org/2003/role/disclosureRef" id="res_21">
      <in-rbi-rep-par:Circular>DBS.No.FBC.BC.3413.12.00199-2000  April 6, 2000</in-rbi-rep-par:Circular>
    </link:reference>
    <link:referenceArc xlink:type="arc" xlink:arcrole="http://www.xbrl.org/2003/arcrole/concept-reference" xlink:from="in-rbi-rep_LessThanUSD1MiliionMember" xlink:to="res_21" />
    <link:loc xlink:type="locator" xlink:href="../core/in-rbi-rep.xsd#in-rbi-rep_NameOfBorrowerAxis" xlink:label="in-rbi-rep_NameOfBorrowerAxis" />
    <link:reference xlink:type="resource" xlink:label="res_22" xlink:role="http://www.xbrl.org/2003/role/disclosureRef" id="res_22">
      <in-rbi-rep-par:Circular>DBS.No.FBC.BC.3413.12.00199-2000  April 6, 2000</in-rbi-rep-par:Circular>
    </link:reference>
    <link:referenceArc xlink:type="arc" xlink:arcrole="http://www.xbrl.org/2003/arcrole/concept-reference" xlink:from="in-rbi-rep_NameOfBorrowerAxis" xlink:to="res_22" />
    <link:loc xlink:type="locator" xlink:href="../core/in-rbi-rep.xsd#in-rbi-rep_BorrowerGroupNameAxis" xlink:label="in-rbi-rep_BorrowerGroupNameAxis" />
    <link:reference xlink:type="resource" xlink:label="res_23" xlink:role="http://www.xbrl.org/2003/role/disclosureRef" id="res_23">
      <in-rbi-rep-par:Circular>DBS.No.FBC.BC.3413.12.00199-2000  April 6, 2000</in-rbi-rep-par:Circular>
    </link:reference>
    <link:referenceArc xlink:type="arc" xlink:arcrole="http://www.xbrl.org/2003/arcrole/concept-reference" xlink:from="in-rbi-rep_BorrowerGroupNameAxis" xlink:to="res_23" />
    <link:loc xlink:type="locator" xlink:href="../core/in-rbi-rep.xsd#in-rbi-rep_IndustryCodeAxis" xlink:label="in-rbi-rep_IndustryCodeAxis" />
    <link:reference xlink:type="resource" xlink:label="res_24" xlink:role="http://www.xbrl.org/2003/role/disclosureRef" id="res_24">
      <in-rbi-rep-par:Circular>DBS.No.FBC.BC.3413.12.00199-2000  April 6, 2000</in-rbi-rep-par:Circular>
    </link:reference>
    <link:referenceArc xlink:type="arc" xlink:arcrole="http://www.xbrl.org/2003/arcrole/concept-reference" xlink:from="in-rbi-rep_IndustryCodeAxis" xlink:to="res_24" />
    <link:loc xlink:type="locator" xlink:href="../core/in-rbi-rep.xsd#in-rbi-rep_MoreThanUSD2MillionMember" xlink:label="in-rbi-rep_MoreThanUSD2MillionMember" />
    <link:reference xlink:type="resource" xlink:label="res_25" xlink:role="http://www.xbrl.org/2003/role/disclosureRef" id="res_25">
      <in-rbi-rep-par:Circular>DBS.No.FBC.BC.3413.12.00199-2000  April 6, 2000</in-rbi-rep-par:Circular>
    </link:reference>
    <link:referenceArc xlink:type="arc" xlink:arcrole="http://www.xbrl.org/2003/arcrole/concept-reference" xlink:from="in-rbi-rep_MoreThanUSD2MillionMember" xlink:to="res_25" />
    <link:loc xlink:type="locator" xlink:href="../core/in-rbi-rep.xsd#in-rbi-rep_LessThanUSD2MillionMember" xlink:label="in-rbi-rep_LessThanUSD2MillionMember" />
    <link:reference xlink:type="resource" xlink:label="res_26" xlink:role="http://www.xbrl.org/2003/role/disclosureRef" id="res_26">
      <in-rbi-rep-par:Circular>DBS.No.FBC.BC.3413.12.00199-2000  April 6, 2000</in-rbi-rep-par:Circular>
    </link:reference>
    <link:referenceArc xlink:type="arc" xlink:arcrole="http://www.xbrl.org/2003/arcrole/concept-reference" xlink:from="in-rbi-rep_LessThanUSD2MillionMember" xlink:to="res_26" />
    <link:loc xlink:type="locator" xlink:href="../core/in-rbi-rep.xsd#in-rbi-rep_ProblemCreditMember" xlink:label="in-rbi-rep_ProblemCreditMember" />
    <link:reference xlink:type="resource" xlink:label="res_27" xlink:role="http://www.xbrl.org/2003/role/disclosureRef" id="res_27">
      <in-rbi-rep-par:Circular>DBS.No.FBC.BC.3413.12.00199-2000  April 6, 2000</in-rbi-rep-par:Circular>
    </link:reference>
    <link:referenceArc xlink:type="arc" xlink:arcrole="http://www.xbrl.org/2003/arcrole/concept-reference" xlink:from="in-rbi-rep_ProblemCreditMember" xlink:to="res_27" />
    <link:loc xlink:type="locator" xlink:href="../core/in-rbi-rep.xsd#in-rbi-rep_ProblemInvestmentMember" xlink:label="in-rbi-rep_ProblemInvestmentMember" />
    <link:reference xlink:type="resource" xlink:label="res_28" xlink:role="http://www.xbrl.org/2003/role/disclosureRef" id="res_28">
      <in-rbi-rep-par:Circular>DBS.No.FBC.BC.3413.12.00199-2000  April 6, 2000</in-rbi-rep-par:Circular>
    </link:reference>
    <link:referenceArc xlink:type="arc" xlink:arcrole="http://www.xbrl.org/2003/arcrole/concept-reference" xlink:from="in-rbi-rep_ProblemInvestmentMember" xlink:to="res_28" />
  </link:referenceLink>
</link:linkbase>