<?xml version="1.0" encoding="utf-8"?>
<!--Generated by IRIS Formula Editor Version : 1.0.0.0-->
<link:linkbase xmlns:xlink="http://www.w3.org/1999/xlink" xmlns:link="http://www.xbrl.org/2003/linkbase" xmlns:generic="http://xbrl.org/2008/generic" xmlns:formula="http://xbrl.org/2008/formula" xmlns:ca="http://xbrl.org/2008/assertion/consistency" xmlns:ea="http://xbrl.org/2008/assertion/existence" xmlns:va="http://xbrl.org/2008/assertion/value" xmlns:variable="http://xbrl.org/2008/variable" xmlns:cf="http://xbrl.org/2008/filter/concept" xmlns:uf="http://xbrl.org/2008/filter/unit" xmlns:pf="http://xbrl.org/2008/filter/period" xmlns:df="http://xbrl.org/2008/filter/dimension" xmlns:ef="http://xbrl.org/2008/filter/entity" xmlns:bf="http://xbrl.org/2008/filter/boolean" xmlns:tf="http://xbrl.org/2008/filter/tuple" xmlns:mf="http://xbrl.org/2008/filter/match" xmlns:label="http://xbrl.org/2008/label" xmlns:v="http://xbrl.org/2008/formula/conformance/variable" xmlns:c="http://xbrl.org/formula/conformance/example" xmlns:iso4217="http://www.xbrl.org/2003/iso4217" xmlns:utr="http://www.xbrl.org/2009/utr" xmlns:msg="http://xbrl.org/2010/message" xmlns:instance="http://www.xbrl.org/2003/instance" xmlns:xsi="http://www.w3.org/2001/XMLSchema-instance" xmlns:fn="http://www.w3.org/2005/xpath-functions" xmlns:xs="http://www.w3.org/2001/XMLSchema" xsi:schemaLocation="http://www.xbrl.org/2003/linkbase http://www.xbrl.org/2003/xbrl-linkbase-2003-12-31.xsd http://xbrl.org/2008/generic http://www.xbrl.org/2008/generic-link.xsd http://xbrl.org/2008/filter/boolean http://www.xbrl.org/2008/boolean-filter.xsd http://xbrl.org/2008/formula http://www.xbrl.org/2008/formula.xsd http://xbrl.org/2008/assertion/consistency http://www.xbrl.org/2008/consistency-assertion.xsd http://xbrl.org/2008/assertion/existence http://www.xbrl.org/2008/existence-assertion.xsd http://xbrl.org/2008/assertion/value http://www.xbrl.org/2008/value-assertion.xsd http://xbrl.org/2008/variable http://www.xbrl.org/2008/variable.xsd http://xbrl.org/2008/filter/period http://www.xbrl.org/2008/period-filter.xsd http://xbrl.org/2008/filter/concept http://www.xbrl.org/2008/concept-filter.xsd http://xbrl.org/2008/filter/tuple http://www.xbrl.org/2008/tuple-filter.xsd http://xbrl.org/2008/filter/dimension http://www.xbrl.org/2008/dimension-filter.xsd http://xbrl.org/2008/filter/general http://www.xbrl.org/2008/general-filter.xsd http://xbrl.org/2008/label http://www.xbrl.org/2008/generic-label.xsd http://xbrl.org/2008/validation http://www.xbrl.org/2008/validation.xsd http://xbrl.org/2008/filter/unit http://www.xbrl.org/2008/unit-filter.xsd http://xbrl.org/2010/message http://www.xbrl.org/2010/generic-message.xsd http://xbrl.org/2008/filter/match http://www.xbrl.org/2008/match-filter.xsd http://xbrl.org/2010/filter/aspect-cover http://www.xbrl.org/2010/aspect-cover-filter.xsd" xmlns:acf="http://xbrl.org/2010/filter/aspect-cover" xmlns:xfi="http://www.xbrl.org/2008/function/instance" xmlns:xbrli="http://www.xbrl.org/2003/instance" xmlns:in-rbi-rep="http://www.rbi.org/in/xbrl/2012-04-25/rbi" xmlns:xbrldt="http://xbrl.org/2005/xbrldt" xmlns:in-rbi-rep-par="http://www.rbi.org/in-rbi-rep-par" xmlns:xl="http://www.xbrl.org/2003/XLink">
  <link:roleRef roleURI="http://www.xbrl.org/2010/role/message" xlink:href="http://www.xbrl.org/2010/generic-message.xsd#standard-message" xlink:type="simple" />
  <link:roleRef roleURI="http://www.xbrl.org/2008/role/label" xlink:href="http://www.xbrl.org/2008/generic-label.xsd#standard-label" xlink:type="simple" />
  <link:roleRef roleURI="http://www.xbrl.org/2008/role/link" xlink:href="http://www.xbrl.org/2008/generic-link.xsd#standard-link-role" xlink:type="simple" />
  <link:arcroleRef arcroleURI="http://xbrl.org/arcrole/2010/assertion-unsatisfied-message" xlink:href="http://www.xbrl.org/2010/validation-message.xsd#assertion-unsatisfied-message" xlink:type="simple" />
  <link:arcroleRef arcroleURI="http://xbrl.org/arcrole/2010/assertion-satisfied-message" xlink:href="http://www.xbrl.org/2010/validation-message.xsd#assertion-satisfied-message" xlink:type="simple" />
  <link:arcroleRef arcroleURI="http://xbrl.org/arcrole/2008/element-label" xlink:href="http://www.xbrl.org/2008/generic-label.xsd#element-label" xlink:type="simple" />
  <link:arcroleRef arcroleURI="http://xbrl.org/arcrole/2008/consistency-assertion-parameter" xlink:href="http://www.xbrl.org/2008/consistency-assertion.xsd#consistency-assertion-parameter" xlink:type="simple" />
  <link:arcroleRef arcroleURI="http://xbrl.org/arcrole/2008/consistency-assertion-formula" xlink:href="http://www.xbrl.org/2008/consistency-assertion.xsd#consistency-assertion-formula" xlink:type="simple" />
  <link:arcroleRef arcroleURI="http://xbrl.org/arcrole/2008/variable-set-precondition" xlink:href="http://www.xbrl.org/2008/variable.xsd#variable-set-precondition" xlink:type="simple" />
  <link:arcroleRef arcroleURI="http://xbrl.org/arcrole/2008/boolean-filter" xlink:href="http://www.xbrl.org/2008/boolean-filter.xsd#boolean-filter" xlink:type="simple" />
  <link:arcroleRef arcroleURI="http://xbrl.org/arcrole/2008/variable-set-filter" xlink:href="http://www.xbrl.org/2008/variable.xsd#variable-set-filter" xlink:type="simple" />
  <link:arcroleRef arcroleURI="http://xbrl.org/arcrole/2008/variable-filter" xlink:href="http://www.xbrl.org/2008/variable.xsd#variable-filter" xlink:type="simple" />
  <link:arcroleRef arcroleURI="http://xbrl.org/arcrole/2008/variable-set" xlink:href="http://www.xbrl.org/2008/variable.xsd#variable-set" xlink:type="simple" />
  <generic:link xlink:type="extended" xmlns:num="http://www.xbrl.org/dtr/type/numeric" xmlns:non-num="http://www.xbrl.org/dtr/type/non-numeric" xlink:role="http://www.xbrl.org/2008/role/link">
    <va:valueAssertion xlink:type="resource" xlink:label="SectionAandB-ConditionalMandatoryCheck" xlink:title="SectionAandB-ConditionalMandatoryCheck" id="SectionAandB-ConditionalMandatoryCheck" test="(if(not(empty($V1))) then (not(empty($V2))) else &quot;False&quot;)" aspectModel="dimensional" implicitFiltering="true" />
    <generic:arc xlink:type="arc" xlink:arcrole="http://xbrl.org/arcrole/2010/assertion-unsatisfied-message" xlink:from="SectionAandB-ConditionalMandatoryCheck" xlink:to="ErrorMessage_1" />
    <msg:message xlink:type="resource" xlink:label="ErrorMessage_1" xlink:role="http://www.xbrl.org/2010/role/message" xml:lang="en" xlink:title="ErrorMessage_1" id="ErrorMessage_1">If Section B is reported then reporting of "Regulatory Capital (Tier-I and Tier-II Capital) of previous March" under Section A is mandatory.</msg:message>
    <variable:variableArc xlink:type="arc" xlink:arcrole="http://xbrl.org/arcrole/2008/variable-set" xlink:from="SectionAandB-ConditionalMandatoryCheck" xlink:to="Var_1" xlink:title="SectionAandB-ConditionalMandatoryCheck_Var_1" order="1" name="V1" />
    <variable:factVariable xlink:type="resource" xlink:label="Var_1" bindAsSequence="true" xlink:title="Var_1" id="Var_1" fallbackValue="()" />
	<acf:aspectCover xlink:type="resource" xlink:label="aspectCover1" xlink:title="aspectCover1" id="aspectCover1">
      <acf:aspect>all</acf:aspect>
    </acf:aspectCover>
    <variable:variableFilterArc xlink:type="arc" xlink:arcrole="http://xbrl.org/arcrole/2008/variable-filter" xlink:from="Var_1" xlink:to="aspectCover1" order="1.0" use="optional" complement="false" cover="true" />
    <variable:variableFilterArc xlink:type="arc" xlink:from="Var_1" xlink:to="Var_1_explicitDimension_1" xlink:arcrole="http://xbrl.org/arcrole/2008/variable-filter" cover="true" complement="false" xlink:title="Var_1_Var_1_explicitDimension_1" order="1" />
    <df:explicitDimension xlink:type="resource" xlink:label="Var_1_explicitDimension_1" xlink:title="Var_1_explicitDimension_1" id="Var_1_explicitDimension_1">
      <df:dimension>
        <df:qname>in-rbi-rep:LargeCreditAxis</df:qname>
      </df:dimension>
      <df:member>
        <df:qname>in-rbi-rep:IndividualBorrowersMember</df:qname>
      </df:member>
    </df:explicitDimension>
    <variable:variableFilterArc xlink:type="arc" xlink:from="Var_1" xlink:to="Var_1_typedDimension_2" xlink:arcrole="http://xbrl.org/arcrole/2008/variable-filter" cover="true" complement="false" xlink:title="Var_1_Var_1_typedDimension_2" order="2" />
    <df:typedDimension xlink:type="resource" xlink:label="Var_1_typedDimension_2" xlink:title="Var_1_typedDimension_2" id="Var_1_typedDimension_2">
      <df:dimension>
        <df:qname>in-rbi-rep:UniqueTransactionCodeAxis</df:qname>
      </df:dimension>
    </df:typedDimension>
    <variable:variableArc xlink:type="arc" xlink:arcrole="http://xbrl.org/arcrole/2008/variable-set" xlink:from="SectionAandB-ConditionalMandatoryCheck" xlink:to="Var_2" xlink:title="SectionAandB-ConditionalMandatoryCheck_Var_2" order="2" name="V2" />
    <variable:factVariable xlink:type="resource" xlink:label="Var_2" bindAsSequence="true" xlink:title="Var_2" id="Var_2" fallbackValue="()" />
	<acf:aspectCover xlink:type="resource" xlink:label="aspectCover2" xlink:title="aspectCover2" id="aspectCover2">
      <acf:aspect>all</acf:aspect>
    </acf:aspectCover>
    <variable:variableFilterArc xlink:type="arc" xlink:arcrole="http://xbrl.org/arcrole/2008/variable-filter" xlink:from="Var_2" xlink:to="aspectCover2" order="1.0" use="optional" complement="false" cover="true" />
    <variable:variableFilterArc xlink:type="arc" xlink:from="Var_2" xlink:to="Var_2_explicitDimension_1" xlink:arcrole="http://xbrl.org/arcrole/2008/variable-filter" cover="true" complement="false" xlink:title="Var_2_Var_2_explicitDimension_1" order="1" />
    <df:explicitDimension xlink:type="resource" xlink:label="Var_2_explicitDimension_1" xlink:title="Var_2_explicitDimension_1" id="Var_2_explicitDimension_1">
      <df:dimension>
        <df:qname>in-rbi-rep:LargeCreditAxis</df:qname>
      </df:dimension>
      <df:member>
        <df:qname>in-rbi-rep:BorrowerGroupMember</df:qname>
      </df:member>
    </df:explicitDimension>
    <variable:variableFilterArc xlink:type="arc" xlink:from="Var_2" xlink:to="Var_2_typedDimension_2" xlink:arcrole="http://xbrl.org/arcrole/2008/variable-filter" cover="true" complement="false" xlink:title="Var_2_Var_2_typedDimension_2" order="2" />
    <df:typedDimension xlink:type="resource" xlink:label="Var_2_typedDimension_2" xlink:title="Var_2_typedDimension_2" id="Var_2_typedDimension_2">
      <df:dimension>
        <df:qname>in-rbi-rep:UniqueTransactionCodeAxis</df:qname>
      </df:dimension>
    </df:typedDimension>
    <df:typedDimension xlink:type="resource" xlink:label="SectionAandB-ConditionalMandatoryCheck_orFilter_1_typedDimension_1" xlink:title="SectionAandB-ConditionalMandatoryCheck_orFilter_1_typedDimension_1" id="SectionAandB-ConditionalMandatoryCheck_orFilter_1_typedDimension_1">
      <df:dimension>
        <df:qname>in-rbi-rep:IndustryCodeAxis</df:qname>
      </df:dimension>
    </df:typedDimension>
    <variable:variableFilterArc xlink:type="arc" xlink:from="SectionAandB-ConditionalMandatoryCheck_orFilter_1" xlink:to="SectionAandB-ConditionalMandatoryCheck_orFilter_1_typedDimension_1" xlink:arcrole="http://xbrl.org/arcrole/2008/boolean-filter" cover="true" complement="false" xlink:title="SectionAandB-ConditionalMandatoryCheck_orFilter_1_SectionAandB-ConditionalMandatoryCheck_orFilter_1_typedDimension_1" order="1" />
    <df:typedDimension xlink:type="resource" xlink:label="SectionAandB-ConditionalMandatoryCheck_orFilter_1_typedDimension_2" xlink:title="SectionAandB-ConditionalMandatoryCheck_orFilter_1_typedDimension_2" id="SectionAandB-ConditionalMandatoryCheck_orFilter_1_typedDimension_2">
      <df:dimension>
        <df:qname>in-rbi-rep:IndustryNameAxis</df:qname>
      </df:dimension>
    </df:typedDimension>
    <variable:variableFilterArc xlink:type="arc" xlink:from="SectionAandB-ConditionalMandatoryCheck_orFilter_1" xlink:to="SectionAandB-ConditionalMandatoryCheck_orFilter_1_typedDimension_2" xlink:arcrole="http://xbrl.org/arcrole/2008/boolean-filter" cover="true" complement="false" xlink:title="SectionAandB-ConditionalMandatoryCheck_orFilter_1_SectionAandB-ConditionalMandatoryCheck_orFilter_1_typedDimension_2" order="2" />
    <df:typedDimension xlink:type="resource" xlink:label="SectionAandB-ConditionalMandatoryCheck_orFilter_1_typedDimension_3" xlink:title="SectionAandB-ConditionalMandatoryCheck_orFilter_1_typedDimension_3" id="SectionAandB-ConditionalMandatoryCheck_orFilter_1_typedDimension_3">
      <df:dimension>
        <df:qname>in-rbi-rep:LeadBankNameAxis</df:qname>
      </df:dimension>
    </df:typedDimension>
    <variable:variableFilterArc xlink:type="arc" xlink:from="SectionAandB-ConditionalMandatoryCheck_orFilter_1" xlink:to="SectionAandB-ConditionalMandatoryCheck_orFilter_1_typedDimension_3" xlink:arcrole="http://xbrl.org/arcrole/2008/boolean-filter" cover="true" complement="false" xlink:title="SectionAandB-ConditionalMandatoryCheck_orFilter_1_SectionAandB-ConditionalMandatoryCheck_orFilter_1_typedDimension_3" order="3" />
    <df:explicitDimension xlink:type="resource" xlink:label="SectionAandB-ConditionalMandatoryCheck_orFilter_1_explicitDimension_4" xlink:title="SectionAandB-ConditionalMandatoryCheck_orFilter_1_explicitDimension_4" id="SectionAandB-ConditionalMandatoryCheck_orFilter_1_explicitDimension_4">
      <df:dimension>
        <df:qname>in-rbi-rep:RegionOfBusinessAxis</df:qname>
      </df:dimension>
    </df:explicitDimension>
    <variable:variableFilterArc xlink:type="arc" xlink:from="SectionAandB-ConditionalMandatoryCheck_orFilter_1" xlink:to="SectionAandB-ConditionalMandatoryCheck_orFilter_1_explicitDimension_4" xlink:arcrole="http://xbrl.org/arcrole/2008/boolean-filter" cover="true" complement="false" xlink:title="SectionAandB-ConditionalMandatoryCheck_orFilter_1_SectionAandB-ConditionalMandatoryCheck_orFilter_1_explicitDimension_4" order="4" />
    <variable:variableSetFilterArc xlink:arcrole="http://xbrl.org/arcrole/2008/variable-set-filter" xlink:from="SectionAandB-ConditionalMandatoryCheck" xlink:to="SectionAandB-ConditionalMandatoryCheck_orFilter_1" complement="false" order="1" xlink:title="SectionAandB-ConditionalMandatoryCheck_SectionAandB-ConditionalMandatoryCheck_orFilter_1" xlink:type="arc" />
    <bf:orFilter xlink:type="resource" xlink:label="SectionAandB-ConditionalMandatoryCheck_orFilter_1" xlink:title="SectionAandB-ConditionalMandatoryCheck_orFilter_1" id="SectionAandB-ConditionalMandatoryCheck_orFilter_1" />
	<va:valueAssertion xlink:type="resource" xlink:label="SectionC-OverseasOperations" xlink:title="SectionC-OverseasOperations" id="SectionC-OverseasOperations" test="((if($V2=&quot;Domestic bank with overseas branches&quot;) then (not(empty($V1))) else &quot;False&quot;) and (if($V2!=&quot;Domestic bank with overseas branches&quot;) then (empty($V1)) else &quot;False&quot;))" aspectModel="dimensional" implicitFiltering="true" />
    <generic:arc xlink:type="arc" xlink:arcrole="http://xbrl.org/arcrole/2010/assertion-unsatisfied-message" xlink:from="SectionC-OverseasOperations" xlink:to="ErrorMessage_2" />
    <msg:message xlink:type="resource" xlink:label="ErrorMessage_2" xlink:role="http://www.xbrl.org/2010/role/message" xml:lang="en" xlink:title="ErrorMessage_2" id="ErrorMessage_2">Reporting of 'Section C Overseas Operations' is applicable only for "Domestic bank with overseas branches".</msg:message>
    <variable:variableArc xlink:type="arc" xlink:arcrole="http://xbrl.org/arcrole/2008/variable-set" xlink:from="SectionC-OverseasOperations" xlink:to="Var_3" xlink:title="SectionC-OverseasOperations_Var_3" order="1" name="V1" />
    <variable:factVariable xlink:type="resource" xlink:label="Var_3" bindAsSequence="true" xlink:title="Var_3" id="Var_3" fallbackValue="()" />
	<acf:aspectCover xlink:type="resource" xlink:label="aspectCover3" xlink:title="aspectCover3" id="aspectCover3">
      <acf:aspect>all</acf:aspect>
    </acf:aspectCover>
    <variable:variableFilterArc xlink:type="arc" xlink:arcrole="http://xbrl.org/arcrole/2008/variable-filter" xlink:from="Var_3" xlink:to="aspectCover3" order="1.0" use="optional" complement="false" cover="true" />
    <variable:variableFilterArc xlink:type="arc" xlink:from="Var_3" xlink:to="Var_3_explicitDimension_1" xlink:arcrole="http://xbrl.org/arcrole/2008/variable-filter" cover="true" complement="false" xlink:title="Var_3_Var_3_explicitDimension_1" order="1" />
    <df:explicitDimension xlink:type="resource" xlink:label="Var_3_explicitDimension_1" xlink:title="Var_3_explicitDimension_1" id="Var_3_explicitDimension_1">
      <df:dimension>
        <df:qname>in-rbi-rep:RegionOfBusinessAxis</df:qname>
      </df:dimension>
      <df:member>
        <df:qname>in-rbi-rep:OverseasMember</df:qname>
      </df:member>
    </df:explicitDimension>
    <variable:variableFilterArc xlink:type="arc" xlink:from="Var_3" xlink:to="Var_3_explicitDimension_2" xlink:arcrole="http://xbrl.org/arcrole/2008/variable-filter" cover="true" complement="false" xlink:title="Var_3_Var_3_explicitDimension_2" order="2" />
    <df:explicitDimension xlink:type="resource" xlink:label="Var_3_explicitDimension_2" xlink:title="Var_3_explicitDimension_2" id="Var_3_explicitDimension_2">
      <df:dimension>
        <df:qname>in-rbi-rep:LargeCreditAxis</df:qname>
      </df:dimension>
      <df:member>
        <df:qname>in-rbi-rep:CounterPartyBankMember</df:qname>
      </df:member>
    </df:explicitDimension>
    <variable:variableArc xlink:type="arc" xlink:arcrole="http://xbrl.org/arcrole/2008/variable-set" xlink:from="SectionC-OverseasOperations" xlink:to="Var_4" xlink:title="SectionC-OverseasOperations_Var_4" order="2" name="V2" />
    <variable:factVariable xlink:type="resource" xlink:label="Var_4" bindAsSequence="false" xlink:title="Var_4" id="Var_4" fallbackValue="()" />
	<acf:aspectCover xlink:type="resource" xlink:label="aspectCover4" xlink:title="aspectCover4" id="aspectCover4">
      <acf:aspect>all</acf:aspect>
    </acf:aspectCover>
    <variable:variableFilterArc xlink:type="arc" xlink:arcrole="http://xbrl.org/arcrole/2008/variable-filter" xlink:from="Var_4" xlink:to="aspectCover4" order="1.0" use="optional" complement="false" cover="true" />
    <variable:variableFilterArc xlink:type="arc" xlink:from="Var_4" xlink:to="Var_4_conceptName_1" xlink:arcrole="http://xbrl.org/arcrole/2008/variable-filter" cover="true" complement="false" xlink:title="Var_4_Var_4_conceptName_1" order="1" />
    <cf:conceptName xlink:type="resource" xlink:title="Var_4_conceptName_1" id="Var_4_conceptName_1" xlink:label="Var_4_conceptName_1">
      <cf:concept>
        <cf:qname>in-rbi-rep:CategoriesOfBanks</cf:qname>
      </cf:concept>
    </cf:conceptName>
	<va:valueAssertion xlink:type="resource" xlink:label="SectionC-GlobalOperations" xlink:title="SectionC-GlobalOperations" id="SectionC-GlobalOperations" test="$V1 = $V2" aspectModel="dimensional" implicitFiltering="true" />
    <generic:arc xlink:type="arc" xlink:arcrole="http://xbrl.org/arcrole/2008/variable-set-precondition" xlink:from="SectionC-GlobalOperations" xlink:to="precondition1" />
    <variable:precondition xlink:type="resource" xlink:label="precondition1" xlink:title="precondition1" id="precondition1" test="$V3 != 'Domestic bank with overseas branches'" />
    <generic:arc xlink:type="arc" xlink:arcrole="http://xbrl.org/arcrole/2010/assertion-unsatisfied-message" xlink:from="SectionC-GlobalOperations" xlink:to="ErrorMessage_3" />
    <msg:message xlink:type="resource" xlink:label="ErrorMessage_3" xlink:role="http://www.xbrl.org/2010/role/message" xml:lang="en" xlink:title="ErrorMessage_3" id="ErrorMessage_3">For "Domestic bank without overseas branches" and "Foreign Banks", values reported for Domestic Operations and Global Operations should be equal.</msg:message>
    <variable:variableArc xlink:type="arc" xlink:arcrole="http://xbrl.org/arcrole/2008/variable-set" xlink:from="SectionC-GlobalOperations" xlink:to="Var_5" xlink:title="SectionC-GlobalOperations_Var_5" order="1" name="V1" />
    <variable:factVariable xlink:type="resource" xlink:label="Var_5" bindAsSequence="false" xlink:title="Var_5" id="Var_5" fallbackValue="()" />
	<acf:aspectCover xlink:type="resource" xlink:label="aspectCover5" xlink:title="aspectCover5" id="aspectCover5">
    <acf:dimension>
    <acf:qname>in-rbi-rep:UniqueTransactionCodeAxis</acf:qname>
    </acf:dimension>
    </acf:aspectCover>
    <variable:variableFilterArc xlink:type="arc" xlink:arcrole="http://xbrl.org/arcrole/2008/variable-filter" xlink:from="Var_5" xlink:to="aspectCover5" order="1.0" use="optional" complement="false" cover="true" />
    <variable:variableFilterArc xlink:type="arc" xlink:from="Var_5" xlink:to="Var_5_explicitDimension_1" xlink:arcrole="http://xbrl.org/arcrole/2008/variable-filter" cover="true" complement="false" xlink:title="Var_5_Var_5_explicitDimension_1" order="1" />
    <df:explicitDimension xlink:type="resource" xlink:label="Var_5_explicitDimension_1" xlink:title="Var_5_explicitDimension_1" id="Var_5_explicitDimension_1">
      <df:dimension>
        <df:qname>in-rbi-rep:RegionOfBusinessAxis</df:qname>
      </df:dimension>
      <df:member>
        <df:qname>in-rbi-rep:DomesticMember</df:qname>
      </df:member>
    </df:explicitDimension>
    <variable:variableArc xlink:type="arc" xlink:arcrole="http://xbrl.org/arcrole/2008/variable-set" xlink:from="SectionC-GlobalOperations" xlink:to="Var_6" xlink:title="SectionC-GlobalOperations_Var_6" order="2" name="V2" />
    <variable:factVariable xlink:type="resource" xlink:label="Var_6" bindAsSequence="false" xlink:title="Var_6" id="Var_6" fallbackValue="()" />
	<acf:aspectCover xlink:type="resource" xlink:label="aspectCover6" xlink:title="aspectCover6" id="aspectCover6">
    <acf:dimension>
    <acf:qname>in-rbi-rep:UniqueTransactionCodeAxis</acf:qname>
    </acf:dimension>
    </acf:aspectCover>
    <variable:variableFilterArc xlink:type="arc" xlink:arcrole="http://xbrl.org/arcrole/2008/variable-filter" xlink:from="Var_6" xlink:to="aspectCover6" order="1.0" use="optional" complement="false" cover="true" />
    <variable:variableFilterArc xlink:type="arc" xlink:from="Var_6" xlink:to="Var_6_explicitDimension_1" xlink:arcrole="http://xbrl.org/arcrole/2008/variable-filter" cover="true" complement="false" xlink:title="Var_6_Var_6_explicitDimension_1" order="1" />
    <df:explicitDimension xlink:type="resource" xlink:label="Var_6_explicitDimension_1" xlink:title="Var_6_explicitDimension_1" id="Var_6_explicitDimension_1">
      <df:dimension>
        <df:qname>in-rbi-rep:RegionOfBusinessAxis</df:qname>
      </df:dimension>
      <df:member>
        <df:qname>in-rbi-rep:GlobalMember</df:qname>
      </df:member>
    </df:explicitDimension>
    <variable:variableArc xlink:type="arc" xlink:arcrole="http://xbrl.org/arcrole/2008/variable-set" xlink:from="SectionC-GlobalOperations" xlink:to="Var_7" xlink:title="SectionC-GlobalOperations_Var_7" order="3" name="V3" />
    <variable:generalVariable xlink:type="resource" xlink:label="Var_7" xlink:title="Var_7" id="Var_7" select="string(//*:CategoriesOfBanks/text())" bindAsSequence="false" />
    <cf:conceptName xlink:type="resource" xlink:title="SectionC-GlobalOperations_orFilter_1_conceptName_1" id="SectionC-GlobalOperations_orFilter_1_conceptName_1" xlink:label="SectionC-GlobalOperations_orFilter_1_conceptName_1">
      <cf:concept>
        <cf:qname>in-rbi-rep:AmountOfFundedExposure</cf:qname>
      </cf:concept>
    </cf:conceptName>
    <variable:variableFilterArc xlink:type="arc" xlink:from="SectionC-GlobalOperations_orFilter_1" xlink:to="SectionC-GlobalOperations_orFilter_1_conceptName_1" xlink:arcrole="http://xbrl.org/arcrole/2008/boolean-filter" cover="true" complement="false" xlink:title="SectionC-GlobalOperations_orFilter_1_SectionC-GlobalOperations_orFilter_1_conceptName_1" order="1" />
    <cf:conceptName xlink:type="resource" xlink:title="SectionC-GlobalOperations_orFilter_1_conceptName_2" id="SectionC-GlobalOperations_orFilter_1_conceptName_2" xlink:label="SectionC-GlobalOperations_orFilter_1_conceptName_2">
      <cf:concept>
        <cf:qname>in-rbi-rep:AmountOfNonFundedExposure</cf:qname>
      </cf:concept>
    </cf:conceptName>
    <variable:variableFilterArc xlink:type="arc" xlink:from="SectionC-GlobalOperations_orFilter_1" xlink:to="SectionC-GlobalOperations_orFilter_1_conceptName_2" xlink:arcrole="http://xbrl.org/arcrole/2008/boolean-filter" cover="true" complement="false" xlink:title="SectionC-GlobalOperations_orFilter_1_SectionC-GlobalOperations_orFilter_1_conceptName_2" order="2" />
    <cf:conceptName xlink:type="resource" xlink:title="SectionC-GlobalOperations_orFilter_1_conceptName_3" id="SectionC-GlobalOperations_orFilter_1_conceptName_3" xlink:label="SectionC-GlobalOperations_orFilter_1_conceptName_3">
      <cf:concept>
        <cf:qname>in-rbi-rep:AggregateCreditExposure</cf:qname>
      </cf:concept>
    </cf:conceptName>
    <variable:variableFilterArc xlink:type="arc" xlink:from="SectionC-GlobalOperations_orFilter_1" xlink:to="SectionC-GlobalOperations_orFilter_1_conceptName_3" xlink:arcrole="http://xbrl.org/arcrole/2008/boolean-filter" cover="true" complement="false" xlink:title="SectionC-GlobalOperations_orFilter_1_SectionC-GlobalOperations_orFilter_1_conceptName_3" order="3" />
    <cf:conceptName xlink:type="resource" xlink:title="SectionC-GlobalOperations_orFilter_1_conceptName_4" id="SectionC-GlobalOperations_orFilter_1_conceptName_4" xlink:label="SectionC-GlobalOperations_orFilter_1_conceptName_4">
      <cf:concept>
        <cf:qname>in-rbi-rep:AggregateExposureAsPercentageOfCapitalFunds</cf:qname>
      </cf:concept>
    </cf:conceptName>
    <variable:variableFilterArc xlink:type="arc" xlink:from="SectionC-GlobalOperations_orFilter_1" xlink:to="SectionC-GlobalOperations_orFilter_1_conceptName_4" xlink:arcrole="http://xbrl.org/arcrole/2008/boolean-filter" cover="true" complement="false" xlink:title="SectionC-GlobalOperations_orFilter_1_SectionC-GlobalOperations_orFilter_1_conceptName_4" order="4" />
    <variable:variableSetFilterArc xlink:arcrole="http://xbrl.org/arcrole/2008/variable-set-filter" xlink:from="SectionC-GlobalOperations" xlink:to="SectionC-GlobalOperations_orFilter_1" complement="false" order="1" xlink:title="SectionC-GlobalOperations_SectionC-GlobalOperations_orFilter_1" xlink:type="arc" />
    <bf:orFilter xlink:type="resource" xlink:label="SectionC-GlobalOperations_orFilter_1" xlink:title="SectionC-GlobalOperations_orFilter_1" id="SectionC-GlobalOperations_orFilter_1" />
	<variable:variableSetFilterArc xlink:arcrole="http://xbrl.org/arcrole/2008/variable-set-filter" xlink:from="SectionC-GlobalOperations" xlink:to="SectionC-GlobalOperations_explicitDimension_2" complement="false" order="2" xlink:title="SectionC-GlobalOperations_SectionC-GlobalOperations_explicitDimension_2" xlink:type="arc" />
    <df:explicitDimension xlink:type="resource" xlink:label="SectionC-GlobalOperations_explicitDimension_2" xlink:title="SectionC-GlobalOperations_explicitDimension_2" id="SectionC-GlobalOperations_explicitDimension_2">
      <df:dimension>
        <df:qname>in-rbi-rep:LargeCreditAxis</df:qname>
      </df:dimension>
      <df:member>
        <df:qname>in-rbi-rep:CounterPartyBankMember</df:qname>
      </df:member>
    </df:explicitDimension>
    <variable:variableSetFilterArc xlink:arcrole="http://xbrl.org/arcrole/2008/variable-set-filter" xlink:from="SectionC-GlobalOperations" xlink:to="SectionC-GlobalOperations_typedDimension_3" complement="false" order="3" xlink:title="SectionC-GlobalOperations_SectionC-GlobalOperations_typedDimension_3" xlink:type="arc" />
    <df:typedDimension xlink:type="resource" xlink:label="SectionC-GlobalOperations_typedDimension_3" xlink:title="SectionC-GlobalOperations_typedDimension_3" id="SectionC-GlobalOperations_typedDimension_3">
      <df:dimension>
        <df:qname>in-rbi-rep:CounterPartyBankNameAxis</df:qname>
      </df:dimension>
    </df:typedDimension>
    <variable:variableSetFilterArc xlink:arcrole="http://xbrl.org/arcrole/2008/variable-set-filter" xlink:from="SectionC-GlobalOperations" xlink:to="SectionC-GlobalOperations_typedDimension_4" complement="false" order="4" xlink:title="SectionC-GlobalOperations_SectionC-GlobalOperations_typedDimension_4" xlink:type="arc" />
    <df:typedDimension xlink:type="resource" xlink:label="SectionC-GlobalOperations_typedDimension_4" xlink:title="SectionC-GlobalOperations_typedDimension_4" id="SectionC-GlobalOperations_typedDimension_4">
      <df:dimension>
        <df:qname>in-rbi-rep:CounterPartyBankDomicileAxis</df:qname>
      </df:dimension>
    </df:typedDimension>
	<va:valueAssertion xlink:type="resource" xlink:label="SectionC-GlobalOperations1" xlink:title="SectionC-GlobalOperations1" id="SectionC-GlobalOperations1" test="$V1 = $V2" aspectModel="dimensional" implicitFiltering="true" />
    <generic:arc xlink:type="arc" xlink:arcrole="http://xbrl.org/arcrole/2008/variable-set-precondition" xlink:from="SectionC-GlobalOperations1" xlink:to="precondition2" />
    <variable:precondition xlink:type="resource" xlink:label="precondition2" xlink:title="precondition2" id="precondition2" test="$V3 != 'Domestic bank with overseas branches'" />
    <generic:arc xlink:type="arc" xlink:arcrole="http://xbrl.org/arcrole/2010/assertion-unsatisfied-message" xlink:from="SectionC-GlobalOperations1" xlink:to="ErrorMessage_4" />
    <msg:message xlink:type="resource" xlink:label="ErrorMessage_4" xlink:role="http://www.xbrl.org/2010/role/message" xml:lang="en" xlink:title="ErrorMessage_4" id="ErrorMessage_4">For "Domestic bank without overseas branches" and "Foreign Banks", values reported for Domestic Operations and Global Operations should be equal.</msg:message>
    <variable:variableArc xlink:type="arc" xlink:arcrole="http://xbrl.org/arcrole/2008/variable-set" xlink:from="SectionC-GlobalOperations1" xlink:to="Var_8" xlink:title="SectionC-GlobalOperations1_Var_8" order="1" name="V1" />
    <variable:factVariable xlink:type="resource" xlink:label="Var_8" bindAsSequence="false" xlink:title="Var_8" id="Var_8" fallbackValue="()" />
    <variable:variableFilterArc xlink:type="arc" xlink:from="Var_8" xlink:to="Var_8_explicitDimension_1" xlink:arcrole="http://xbrl.org/arcrole/2008/variable-filter" cover="true" complement="false" xlink:title="Var_8_Var_8_explicitDimension_1" order="1" />
    <df:explicitDimension xlink:type="resource" xlink:label="Var_8_explicitDimension_1" xlink:title="Var_8_explicitDimension_1" id="Var_8_explicitDimension_1">
      <df:dimension>
        <df:qname>in-rbi-rep:RegionOfBusinessAxis</df:qname>
      </df:dimension>
      <df:member>
        <df:qname>in-rbi-rep:DomesticMember</df:qname>
      </df:member>
    </df:explicitDimension>
    <variable:variableFilterArc xlink:type="arc" xlink:from="Var_8" xlink:to="Var_8_explicitDimension_2" xlink:arcrole="http://xbrl.org/arcrole/2008/variable-filter" cover="true" complement="false" xlink:title="Var_8_Var_8_explicitDimension_2" order="2" />
    <df:explicitDimension xlink:type="resource" xlink:label="Var_8_explicitDimension_2" xlink:title="Var_8_explicitDimension_2" id="Var_8_explicitDimension_2">
      <df:dimension>
        <df:qname>in-rbi-rep:LargeCreditAxis</df:qname>
      </df:dimension>
      <df:member>
        <df:qname>in-rbi-rep:CounterPartyBankMember</df:qname>
      </df:member>
    </df:explicitDimension>
    <variable:variableArc xlink:type="arc" xlink:arcrole="http://xbrl.org/arcrole/2008/variable-set" xlink:from="SectionC-GlobalOperations1" xlink:to="Var_9" xlink:title="SectionC-GlobalOperations1_Var_9" order="2" name="V2" />
    <variable:factVariable xlink:type="resource" xlink:label="Var_9" bindAsSequence="false" xlink:title="Var_9" id="Var_9" fallbackValue="()" />
    <variable:variableFilterArc xlink:type="arc" xlink:from="Var_9" xlink:to="Var_9_explicitDimension_1" xlink:arcrole="http://xbrl.org/arcrole/2008/variable-filter" cover="true" complement="false" xlink:title="Var_9_Var_9_explicitDimension_1" order="1" />
    <df:explicitDimension xlink:type="resource" xlink:label="Var_9_explicitDimension_1" xlink:title="Var_9_explicitDimension_1" id="Var_9_explicitDimension_1">
      <df:dimension>
        <df:qname>in-rbi-rep:RegionOfBusinessAxis</df:qname>
      </df:dimension>
      <df:member>
        <df:qname>in-rbi-rep:GlobalMember</df:qname>
      </df:member>
    </df:explicitDimension>
    <variable:variableFilterArc xlink:type="arc" xlink:from="Var_9" xlink:to="Var_9_explicitDimension_2" xlink:arcrole="http://xbrl.org/arcrole/2008/variable-filter" cover="true" complement="false" xlink:title="Var_9_Var_9_explicitDimension_2" order="2" />
    <df:explicitDimension xlink:type="resource" xlink:label="Var_9_explicitDimension_2" xlink:title="Var_9_explicitDimension_2" id="Var_9_explicitDimension_2">
      <df:dimension>
        <df:qname>in-rbi-rep:LargeCreditAxis</df:qname>
      </df:dimension>
      <df:member>
        <df:qname>in-rbi-rep:CounterPartyBankMember</df:qname>
      </df:member>
    </df:explicitDimension>
    <variable:variableArc xlink:type="arc" xlink:arcrole="http://xbrl.org/arcrole/2008/variable-set" xlink:from="SectionC-GlobalOperations1" xlink:to="Var_10" xlink:title="SectionC-GlobalOperations1_Var_10" order="3" name="V3" />
    <variable:generalVariable xlink:type="resource" xlink:label="Var_10" xlink:title="Var_10" id="Var_10" select="string(//*:CategoriesOfBanks/text())" bindAsSequence="false" />
    <df:typedDimension xlink:type="resource" xlink:label="SectionC-GlobalOperations1_orFilter_1_typedDimension_1" xlink:title="SectionC-GlobalOperations1_orFilter_1_typedDimension_1" id="SectionC-GlobalOperations1_orFilter_1_typedDimension_1">
      <df:dimension>
        <df:qname>in-rbi-rep:CounterPartyBankNameAxis</df:qname>
      </df:dimension>
    </df:typedDimension>
    <variable:variableFilterArc xlink:type="arc" xlink:from="SectionC-GlobalOperations1_orFilter_1" xlink:to="SectionC-GlobalOperations1_orFilter_1_typedDimension_1" xlink:arcrole="http://xbrl.org/arcrole/2008/boolean-filter" cover="true" complement="false" xlink:title="SectionC-GlobalOperations1_orFilter_1_SectionC-GlobalOperations1_orFilter_1_typedDimension_1" order="1" />
    <df:typedDimension xlink:type="resource" xlink:label="SectionC-GlobalOperations1_orFilter_1_typedDimension_2" xlink:title="SectionC-GlobalOperations1_orFilter_1_typedDimension_2" id="SectionC-GlobalOperations1_orFilter_1_typedDimension_2">
      <df:dimension>
        <df:qname>in-rbi-rep:CounterPartyBankDomicileAxis</df:qname>
      </df:dimension>
    </df:typedDimension>
    <variable:variableFilterArc xlink:type="arc" xlink:from="SectionC-GlobalOperations1_orFilter_1" xlink:to="SectionC-GlobalOperations1_orFilter_1_typedDimension_2" xlink:arcrole="http://xbrl.org/arcrole/2008/boolean-filter" cover="true" complement="false" xlink:title="SectionC-GlobalOperations1_orFilter_1_SectionC-GlobalOperations1_orFilter_1_typedDimension_2" order="2" />
    <df:typedDimension xlink:type="resource" xlink:label="SectionC-GlobalOperations1_orFilter_1_typedDimension_3" xlink:title="SectionC-GlobalOperations1_orFilter_1_typedDimension_3" id="SectionC-GlobalOperations1_orFilter_1_typedDimension_3">
      <df:dimension>
        <df:qname>in-rbi-rep:UniqueTransactionCodeAxis</df:qname>
      </df:dimension>
    </df:typedDimension>
    <variable:variableFilterArc xlink:type="arc" xlink:from="SectionC-GlobalOperations1_orFilter_1" xlink:to="SectionC-GlobalOperations1_orFilter_1_typedDimension_3" xlink:arcrole="http://xbrl.org/arcrole/2008/boolean-filter" cover="true" complement="false" xlink:title="SectionC-GlobalOperations1_orFilter_1_SectionC-GlobalOperations1_orFilter_1_typedDimension_3" order="3" />
    <variable:variableSetFilterArc xlink:arcrole="http://xbrl.org/arcrole/2008/variable-set-filter" xlink:from="SectionC-GlobalOperations1" xlink:to="SectionC-GlobalOperations1_orFilter_1" complement="true" order="1" xlink:title="SectionC-GlobalOperations1_SectionC-GlobalOperations1_orFilter_1" xlink:type="arc" />
    <bf:orFilter xlink:type="resource" xlink:label="SectionC-GlobalOperations1_orFilter_1" xlink:title="SectionC-GlobalOperations1_orFilter_1" id="SectionC-GlobalOperations1_orFilter_1" />	
  </generic:link>
</link:linkbase>